{
  "pointLight1": {
    "castShadow": true,
    "color": "#ffffff",
    "decay": 2,
    "distance": 105,
    "intensity": 4,
    "name": "pointLight1",
    "x": -25.25,
    "y": 53.5,
    "z": 11,
    "visible": true
  },
  "pointLight2": {
    "castShadow": false,
    "color": "#ffffff",
    "decay": 2,
    "distance": 200,
    "intensity": 0.5,
    "name": "pointLight2",
    "x": -6.75,
    "y": 37.25,
    "z": -100,
    "visible": true
  },
  "pointLight3": {
    "castShadow": false,
    "color": "#84c8c4",
    "decay": 2,
    "distance": 26.25,
    "intensity": 7.75,
    "name": "pointLight3",
    "x": -6,
    "y": 27.25,
    "z": 3,
    "visible": true
  },
  "pointLight4": {
    "castShadow": true,
    "color": "#7ae9e3",
    "decay": 2,
    "distance": 22.5,
    "intensity": 200,
    "name": "pointLight4",
    "x": -3.45148,
    "y": 39.25,
    "z": -0.675024,
    "visible": true
  },
  "pointLight5": {
    "castShadow": false,
    "color": "#7ae9e3",
    "decay": 2,
    "distance": 27.75,
    "intensity": 1.25,
    "name": "pointLight5",
    "x": -6,
    "y": 21.25,
    "z": 5,
    "visible": false
  },
  "pointLight6": {
    "castShadow": false,
    "color": "#7ae9e3",
    "decay": 2,
    "distance": 27.75,
    "intensity": 1.25,
    "name": "pointLight6",
    "x": -6,
    "y": 21.25,
    "z": 6,
    "visible": false
  }
}
